README.rst
setup.py
sidekick/properties/__init__.py
sidekick/properties/properties.py
sidekick/properties/py.typed
sidekick_properties.egg-info/PKG-INFO
sidekick_properties.egg-info/SOURCES.txt
sidekick_properties.egg-info/dependency_links.txt
sidekick_properties.egg-info/requires.txt
sidekick_properties.egg-info/top_level.txt