Metadata-Version: 2.1
Name: sidekick-properties
Version: 0.1.0
Summary: Lazy properties and attributes for sidekick.
Home-page: https://sidekick.readthedocs.io/
Author: Fábio Macêdo Mendes
Author-email: fabiomacedomendes@gmail.com
License: MIT License
Platform: any
Classifier: Intended Audience :: Developers
Classifier: Development Status :: 5 - Production/Stable
Classifier: License :: OSI Approved :: MIT License
Classifier: Operating System :: OS Independent
Classifier: Programming Language :: Python
Classifier: Programming Language :: Python :: 3
Classifier: Programming Language :: Python :: 3.6
Classifier: Programming Language :: Python :: 3.7
Classifier: Programming Language :: Python :: 3.8
Classifier: Programming Language :: Python :: 3.9
Classifier: Programming Language :: Python :: 3.10
Classifier: Topic :: Software Development :: Libraries
Classifier: Topic :: Utilities
Classifier: Typing :: Typed
Requires-Python: >=3.6
Provides-Extra: extra
